Metadata-Version: 1.1
Name: cpyc
Version: 0.0.1
Summary: cpyc
Home-page: UNKNOWN
Author: bnbdr
Author-email: bad.32@outlook.com
License: MIT
Keywords: cpyc
Platform: UNKNOWN
Classifier: Intended Audience :: Developers
Classifier: Programming Language :: Python :: 2
Classifier: Programming Language :: Python :: 3
Classifier: License :: OSI Approved :: MIT License
Classifier: Operating System :: OS Independent
